azure_functions_doctor/__init__.py
azure_functions_doctor/api.py
azure_functions_doctor/cli.py
azure_functions_doctor/config.py
azure_functions_doctor/doctor.py
azure_functions_doctor/handlers.py
azure_functions_doctor/logging_config.py
azure_functions_doctor/py.typed
azure_functions_doctor/target_resolver.py
azure_functions_doctor/utils.py
azure_functions_doctor/assets/__init__.py
azure_functions_doctor/assets/rules.json
azure_functions_doctor/assets/rules/v1.json
azure_functions_doctor/assets/rules/v2.json
azure_functions_doctor/schemas/rules.schema.json
azure_functions_doctor-0.14.0.dist-info/METADATA
azure_functions_doctor-0.14.0.dist-info/WHEEL
azure_functions_doctor-0.14.0.dist-info/entry_points.txt
azure_functions_doctor-0.14.0.dist-info/licenses/LICENSE
azure_functions_doctor-0.14.0.dist-info/RECORD
